giotto_viewer/__init__.py
giotto_viewer/finished
giotto_viewer/giotto_copy_js_css.py
giotto_viewer/giotto_setup_image.py
giotto_viewer/giotto_setup_viewer.py
giotto_viewer/giotto_step1_modify_json.py
giotto_viewer/prepare_annot.py
giotto_viewer/read_matrix_custom.py
giotto_viewer/css/L.Control.MousePosition.css
giotto_viewer/css/bootstrap.4.1.0.min.css
giotto_viewer/css/font-awesome.4.7.0.min.css
giotto_viewer/css/jquery-ui.min.css
giotto_viewer/css/leaflet.css
giotto_viewer/js/L.Control.MousePosition.js
giotto_viewer/js/L.Map.Sync.js
giotto_viewer/js/bootstrap.4.1.0.min.js
giotto_viewer/js/jquery-ui.min.js
giotto_viewer/js/jquery.3.3.1.min.js
giotto_viewer/js/leaflet-lasso-2.js
giotto_viewer/js/leaflet.js
giotto_viewer/js/popper.min.js
giotto_viewer/js/script.stitched.class.js
giotto_viewer-1.0.8.dist-info/METADATA
giotto_viewer-1.0.8.dist-info/WHEEL
giotto_viewer-1.0.8.dist-info/entry_points.txt
giotto_viewer-1.0.8.dist-info/top_level.txt
giotto_viewer-1.0.8.dist-info/RECORD
