Metadata-Version: 2.1
Name: giotto-viewer
Version: 1.0.8
Summary: giotto-viewer is a web-based locally hosted visualization tool for spatial transcriptomic data
Home-page: http://spatial.rc.fas.harvard.edu
Author: Qian Zhu
Author-email: zqian@jimmy.harvard.edu
License: UNKNOWN
Platform: UNKNOWN
Classifier: Programming Language :: Python :: 3
Classifier: License :: OSI Approved :: MIT License
Classifier: Operating System :: OS Independent
Requires-Python: >=3.5
Requires-Dist: jsbeautifier
Requires-Dist: matplotlib
Requires-Dist: numpy
Requires-Dist: pandas
Requires-Dist: scipy
Requires-Dist: seaborn
